{"name":"Edgerouter vpc bgp dual wan","tagline":"Edgerouter + Edgemax 1.7 + dual WAN failover + AWS VPC VPN Failover + BGP","body":"# Edgerouter + Edgemax 1.7 + dual WAN failover + AWS VPC VPN Failover + BGP\r\n\r\nThis is a basic configuration for Edgerouter with EdgeOS 1.7, dual WAN Failover and two AWS VPC VPN connections routed with BGP.\r\n\r\nWAN1 : ETH0 with pppoe and static IP\r\n\r\nWAN2 : ETH1 with DHCP and dynamic IP\r\n\r\nLAN : ETH3\r\n\r\n\r\nFrom the VPC - VPN Connections, you can downlad the configuration for Vyatta software and apply it directly to the router, as they are compatible.\r\n\r\n\r\n\r\n","google":"","note":"Don't delete this file! It's used internally to help with page regeneration."}